LICENSE
MANIFEST.in
README.md
pyproject.toml
netbox_maintenance/__init__.py
netbox_maintenance/navigation.py
netbox_maintenance/search.py
netbox_maintenance/template_content.py
netbox_maintenance/urls.py
netbox_maintenance/widgets.py
netbox_maintenance.egg-info/PKG-INFO
netbox_maintenance.egg-info/SOURCES.txt
netbox_maintenance.egg-info/dependency_links.txt
netbox_maintenance.egg-info/requires.txt
netbox_maintenance.egg-info/top_level.txt
netbox_maintenance/api/__init__.py
netbox_maintenance/api/urls.py
netbox_maintenance/api/serializers/__init__.py
netbox_maintenance/api/serializers/maintenance.py
netbox_maintenance/api/serializers/maintenance_impact.py
netbox_maintenance/api/serializers/maintenance_impact_types.py
netbox_maintenance/api/serializers/maintenance_types.py
netbox_maintenance/api/views/__init__.py
netbox_maintenance/api/views/maintenance.py
netbox_maintenance/api/views/maintenance_impact.py
netbox_maintenance/api/views/maintenance_impact_types.py
netbox_maintenance/api/views/maintenance_types.py
netbox_maintenance/filtersets/__init__.py
netbox_maintenance/filtersets/maintenance.py
netbox_maintenance/filtersets/maintenance_impact.py
netbox_maintenance/filtersets/maintenance_impact_types.py
netbox_maintenance/filtersets/maintenance_types.py
netbox_maintenance/forms/__init__.py
netbox_maintenance/forms/maintenance.py
netbox_maintenance/forms/maintenance_impact.py
netbox_maintenance/forms/maintenance_impact_types.py
netbox_maintenance/forms/maintenance_types.py
netbox_maintenance/graphql/__init__.py
netbox_maintenance/graphql/filters.py
netbox_maintenance/graphql/schema.py
netbox_maintenance/graphql/types.py
netbox_maintenance/migrations/0001_initial.py
netbox_maintenance/migrations/__init__.py
netbox_maintenance/models/__init__.py
netbox_maintenance/models/maintenance.py
netbox_maintenance/models/maintenance_impact.py
netbox_maintenance/models/maintenance_types.py
netbox_maintenance/static/.gitkeep
netbox_maintenance/static/maintenance_impact_active_tab.js
netbox_maintenance/static/maintenance_parent_display.js
netbox_maintenance/tables/__init__.py
netbox_maintenance/tables/maintenance.py
netbox_maintenance/tables/maintenance_impact.py
