Metadata-Version: 2.4
Name: netbox_maintenance
Version: 0.1.0b1
Summary: NetBox plugin for managing maintenance windows and scheduled maintenance activities.
Author-email: Your Name <your.email@example.com>
License: Apache-2.0
Project-URL: Homepage, https://github.com/yourusername/netbox-maintenance
Project-URL: Repository, https://github.com/yourusername/netbox-maintenance
Project-URL: Issues, https://github.com/yourusername/netbox-maintenance/issues
Classifier: Development Status :: 3 - Alpha
Classifier: Intended Audience :: Developers
Classifier: Framework :: Django
Classifier: License :: OSI Approved :: Apache Software License
Classifier: Operating System :: OS Independent
Classifier: Programming Language :: Python :: 3 :: Only
Classifier: Programming Language :: Python :: 3.10
Classifier: Programming Language :: Python :: 3.11
Classifier: Programming Language :: Python :: 3.12
Requires-Python: >=3.10
License-File: LICENSE
Provides-Extra: dev
Requires-Dist: black; extra == "dev"
Requires-Dist: autopep8; extra == "dev"
Requires-Dist: pip; extra == "dev"
Requires-Dist: check-manifest; extra == "dev"
Requires-Dist: pytest; extra == "dev"
Requires-Dist: python-dotenv; extra == "dev"
Dynamic: license-file
